DailyData/__init__.py
DailyData/__main__.py
DailyData/config.json
DailyData/analyzer/__init__.py
DailyData/analyzer/compile_journal.py
DailyData/analyzer/config.py
DailyData/analyzer/parse_docx.py
DailyData/time_management/__init__.py
DailyData/time_management/__main__.py
DailyData/tracker/__init__.py
DailyData/tracker/__main__.py
DailyData/tracker/config.py
DailyData/tracker/journaller.py
DailyData-0.0.1.post0.dist-info/LICENSE
DailyData-0.0.1.post0.dist-info/METADATA
DailyData-0.0.1.post0.dist-info/WHEEL
DailyData-0.0.1.post0.dist-info/entry_points.txt
DailyData-0.0.1.post0.dist-info/top_level.txt
DailyData-0.0.1.post0.dist-info/RECORD
