Metadata-Version: 2.1
Name: DailyData
Version: 0.0.1.post0
Summary: A package for recording and reviewing data about your day
Home-page: https://github.com/JEElsner/DailyData/
Author: Jonathan Elsner
Author-email: jeelsner@outlook.com
License: UNKNOWN
Platform: UNKNOWN
Requires-Python: >=3.6
Requires-Dist: ConsoleQuestionPrompts
Requires-Dist: python-docx
Requires-Dist: pandas
Requires-Dist: numpy
